pydantic_educacode/__init__.py
pydantic_educacode/model.py
pydantic_educacode-0.0.4.dist-info/LICENSE
pydantic_educacode-0.0.4.dist-info/METADATA
pydantic_educacode-0.0.4.dist-info/WHEEL
pydantic_educacode-0.0.4.dist-info/top_level.txt
pydantic_educacode-0.0.4.dist-info/RECORD
