Metadata-Version: 2.1
Name: pydantic-educacode
Version: 0.0.4
Summary: A small pydantic extension
Author-email: Clément Marlier <clement.marlier@gmail.com>
Project-URL: Homepage, https://github.com/pypa/sampleproject
Project-URL: Bug Tracker, https://github.com/pypa/sampleproject/issues
Classifier: Programming Language :: Python :: 3
Classifier: License :: OSI Approved :: MIT License
Classifier: Operating System :: OS Independent
Requires-Python: >=3.7
License-File: LICENSE
Requires-Dist: pydantic
